{
    "image": "Camera/ 00000337 .jpg",
    "point_cloud": "LiDAR/ 00000337 .pcd",
    "meta": {
        "time": "Night",
        "environment": "Indoor",
        "weather": "None",
        "place": "Large",
        "city": "Gwangju",
        "terrain": "Urban",
        "road_type": "ge 4m",
        "road_material": "Paved"
    },
    "calib": {
        "intrinsic": [
            [ 1397.991371 , 0.0 , 960.0 ],
            [ 0.0 , 1397.991371 , 540.0 ],
            [ 0.0 , 0.0 , 1.0 ]
        ],
        "rotation": [ -0.96517669 , -1.502906215 , 2.560259924 ],
        "translation": [ 0.13620099 , 1.34389899 , 1.35197656 ]
    },
    "bbox2d": [
        {
            "name": "Car",
            "occluded": false,
            "bbox": [ 0.0 , 665.31 , 17.02 , 792.8 ],
            "status": "Parked"
        },
        {
            "name": "Car",
            "occluded": true,
            "bbox": [ 993.6 , 599.62 , 1115.14 , 655.3 ],
            "status": "Parked"
        },
        {
            "name": "Car",
            "occluded": true,
            "bbox": [ 1020.3 , 597.87 , 1229.09 , 669.8 ],
            "status": "Parked"
        },
        {
            "name": "Car",
            "occluded": true,
            "bbox": [ 1104.3 , 587.4 , 1570.28 , 726.21 ],
            "status": "Parked"
        },
        {
            "name": "Car",
            "occluded": true,
            "bbox": [ 1554.4 , 603.1 , 1811.74 , 709.2 ],
            "status": "Parked"
        },
        {
            "name": "Car",
            "occluded": true,
            "bbox": [ 1777.47 , 600.5 , 1920.0 , 714.4 ],
            "status": "Parked"
        },
        {
            "name": "Car",
            "occluded": true,
            "bbox": [ 354.96 , 548.01 , 687.1 , 675.0 ],
            "status": "Parked"
        },
        {
            "name": "Car",
            "occluded": true,
            "bbox": [ 322.16 , 561.13 , 638.6 , 684.2 ],
            "status": "Parked"
        },
        {
            "name": "Car",
            "occluded": true,
            "bbox": [ 185.68 , 565.07 , 563.8 , 734.1 ],
            "status": "Parked"
        },
        {
            "name": "Car",
            "occluded": true,
            "bbox": [ 103.01 , 523.07 , 408.9 , 816.8 ],
            "status": "Parked"
        },
        {
            "name": "Car",
            "occluded": true,
            "bbox": [ 706.65 , 614.93 , 771.1 , 654.0 ],
            "status": "Parked"
        },
        {
            "name": "Car",
            "occluded": true,
            "bbox": [ 641.04 , 596.56 , 747.5 , 654.0 ],
            "status": "Parked"
        },
        {
            "name": "Car",
            "occluded": true,
            "bbox": [ 655.47 , 616.25 , 712.1 , 663.2 ],
            "status": "Parked"
        },
        {
            "name": "Parking Block",
            "occluded": false,
            "bbox": [ 1780.59 , 756.48 , 1887.4 , 798.6 ]
        }
    ],
    "segmentation": [
        {
            "name": "Driveable Space",
            "polygon": [
                [ 1806.59 , 997.05 ],
                [ 1079.06 , 687.96 ],
                [ 1110.96 , 687.21 ],
                [ 1110.2 , 684.17 ],
                [ 1108.68 , 680.37 ],
                [ 1107.92 , 677.33 ],
                [ 1107.92 , 675.05 ],
                [ 1107.92 , 672.02 ],
                [ 1108.68 , 669.74 ],
                [ 1032.74 , 669.74 ],
                [ 946.93 , 634.81 ],
                [ 818.58 , 634.81 ],
                [ 0.0 , 915.01 ],
                [ 0.0 , 992.39 ],
                [ 482.92 , 960.6 ],
                [ 914.27 , 956.04 ],
                [ 1353.97 , 968.19 ]
            ]
        },
        {
            "name": "Parking Space",
            "size": "Normal",
            "pattern": "Perpendicular",
            "polygon": [
                [ 1332.7 , 784.7 ],
                [ 1916.9 , 797.9 ],
                [ 1820.9 , 765.9 ],
                [ 1257.3 , 754.5 ]
            ]
        },
        {
            "name": "Parking Space",
            "size": "Normal",
            "pattern": "Perpendicular",
            "polygon": [
                [ 1460.0 , 837.9 ],
                [ 1920.0 , 845.7 ],
                [ 1920.0 , 816.67 ],
                [ 1920.0 , 802.8 ],
                [ 1344.9 , 789.4 ]
            ]
        },
        {
            "name": "Parking Space",
            "size": "Normal",
            "pattern": "Perpendicular",
            "polygon": [
                [ 1845.84 , 992.08 ],
                [ 1914.08 , 988.14 ],
                [ 1918.02 , 889.72 ],
                [ 1593.89 , 885.78 ]
            ]
        }
    ],
    "bbox3d": []
}