{
    "image": "Camera/ 00000342 .jpg",
    "point_cloud": "LiDAR/ 00000342 .pcd",
    "meta": {
        "time": "Night",
        "environment": "Indoor",
        "weather": "None",
        "place": "Large",
        "city": "Gwangju",
        "terrain": "Urban",
        "road_type": "ge 4m",
        "road_material": "Paved"
    },
    "calib": {
        "intrinsic": [
            [ 1397.991371 , 0.0 , 960.0 ],
            [ 0.0 , 1397.991371 , 540.0 ],
            [ 0.0 , 0.0 , 1.0 ]
        ],
        "rotation": [ -0.96517669 , -1.502906215 , 2.560259924 ],
        "translation": [ 0.13620099 , 1.34389899 , 1.35197656 ]
    },
    "bbox2d": [
        {
            "name": "Car",
            "occluded": true,
            "bbox": [ 672.7 , 612.32 , 751.3 , 648.8 ],
            "status": "Parked"
        },
        {
            "name": "Car",
            "occluded": true,
            "bbox": [ 675.32 , 592.63 , 776.2 , 646.2 ],
            "status": "Parked"
        },
        {
            "name": "Parking Block",
            "occluded": false,
            "bbox": [ 1796.34 , 760.41 , 1907.0 , 795.9 ]
        },
        {
            "name": "Car",
            "occluded": true,
            "bbox": [ 0.0 , 546.06 , 467.0 , 772.8 ],
            "status": "Parked"
        },
        {
            "name": "Car",
            "occluded": false,
            "bbox": [ 0.0 , 577.56 , 183.5 , 855.4 ],
            "status": "Parked"
        },
        {
            "name": "Car",
            "occluded": true,
            "bbox": [ 593.96 , 588.7 , 717.1 , 660.6 ],
            "status": "Parked"
        },
        {
            "name": "Car",
            "occluded": true,
            "bbox": [ 593.96 , 607.07 , 675.2 , 671.1 ],
            "status": "Parked"
        },
        {
            "name": "Car",
            "occluded": true,
            "bbox": [ 260.64 , 538.83 , 641.0 , 688.1 ],
            "status": "Parked"
        },
        {
            "name": "Car",
            "occluded": true,
            "bbox": [ 997.3 , 598.46 , 1132.08 , 655.6 ],
            "status": "Parked"
        },
        {
            "name": "Car",
            "occluded": true,
            "bbox": [ 175.35 , 549.33 , 583.3 , 713.1 ],
            "status": "Parked"
        },
        {
            "name": "Car",
            "occluded": true,
            "bbox": [ 1138.6 , 574.26 , 1700.04 , 743.3 ],
            "status": "Parked"
        },
        {
            "name": "Car",
            "occluded": true,
            "bbox": [ 1654.3 , 591.32 , 1920.0 , 727.5 ],
            "status": "Parked"
        },
        {
            "name": "Car",
            "occluded": true,
            "bbox": [ 1015.2 , 591.32 , 1260.43 , 672.4 ],
            "status": "Parked"
        }
    ],
    "segmentation": [
        {
            "name": "Driveable Space",
            "polygon": [
                [ 1764.35 , 975.67 ],
                [ 1095.09 , 694.85 ],
                [ 1137.08 , 694.85 ],
                [ 1137.08 , 673.85 ],
                [ 1028.17 , 673.85 ],
                [ 945.49 , 635.8 ],
                [ 805.08 , 633.17 ],
                [ 4.59 , 902.19 ],
                [ 0.0 , 995.3 ],
                [ 417.96 , 959.93 ],
                [ 854.95 , 948.12 ],
                [ 1315.55 , 957.3 ],
                [ 1806.34 , 992.73 ]
            ]
        },
        {
            "name": "Parking Space",
            "size": "Normal",
            "pattern": "Perpendicular",
            "polygon": [
                [ 1346.38 , 784.26 ],
                [ 1907.0 , 795.9 ],
                [ 1738.24 , 763.0 ],
                [ 1268.92 , 757.68 ]
            ]
        },
        {
            "name": "Parking Space",
            "size": "Normal",
            "pattern": "Perpendicular",
            "polygon": [
                [ 1495.22 , 844.25 ],
                [ 1918.22 , 846.53 ],
                [ 1918.22 , 799.45 ],
                [ 1365.36 , 794.13 ]
            ]
        },
        {
            "name": "Parking Space",
            "size": "Normal",
            "pattern": "Perpendicular",
            "polygon": [
                [ 1520.29 , 856.55 ],
                [ 1783.04 , 960.6 ],
                [ 1918.22 , 960.6 ],
                [ 1919.74 , 856.56 ]
            ]
        },
        {
            "name": "Parking Space",
            "size": "Normal",
            "pattern": "Perpendicular",
            "polygon": [
                [ 85.37 , 832.26 ],
                [ 155.69 , 832.7 ],
                [ 324.45 , 783.92 ],
                [ 182.06 , 781.72 ],
                [ 175.91 , 785.68 ],
                [ 169.31 , 787.44 ],
                [ 162.72 , 789.2 ],
                [ 156.13 , 790.07 ],
                [ 148.66 , 790.07 ],
                [ 141.63 , 790.07 ],
                [ 135.03 , 789.2 ],
                [ 128.44 , 790.07 ],
                [ 121.85 , 792.27 ],
                [ 115.7 , 795.35 ],
                [ 109.54 , 800.18 ],
                [ 104.27 , 805.46 ],
                [ 99.44 , 810.29 ],
                [ 96.36 , 816.44 ],
                [ 95.48 , 823.04 ],
                [ 93.28 , 829.63 ]
            ]
        }
    ],
    "bbox3d": []
}