{
    "image": "Camera/ 00000340 .jpg",
    "point_cloud": "LiDAR/ 00000340 .pcd",
    "meta": {
        "time": "Night",
        "environment": "Indoor",
        "weather": "None",
        "place": "Large",
        "city": "Gwangju",
        "terrain": "Urban",
        "road_type": "ge 4m",
        "road_material": "Paved"
    },
    "calib": {
        "intrinsic": [
            [ 1397.991371 , 0.0 , 960.0 ],
            [ 0.0 , 1397.991371 , 540.0 ],
            [ 0.0 , 0.0 , 1.0 ]
        ],
        "rotation": [ -0.96517669 , -1.502906215 , 2.560259924 ],
        "translation": [ 0.13620099 , 1.34389899 , 1.35197656 ]
    },
    "bbox2d": [
        {
            "name": "Car",
            "occluded": true,
            "bbox": [ 280.17 , 546.69 , 658.3 , 680.3 ],
            "status": "Parked"
        },
        {
            "name": "Car",
            "occluded": true,
            "bbox": [ 997.1 , 593.95 , 1129.36 , 653.1 ],
            "status": "Parked"
        },
        {
            "name": "Car",
            "occluded": true,
            "bbox": [ 1019.0 , 593.95 , 1254.02 , 665.8 ],
            "status": "Parked"
        },
        {
            "name": "Car",
            "occluded": true,
            "bbox": [ 1127.9 , 575.6 , 1652.96 , 739.33 ],
            "status": "Parked"
        },
        {
            "name": "Car",
            "occluded": true,
            "bbox": [ 1616.06 , 590.0 , 1799.3 , 722.3 ],
            "status": "Parked"
        },
        {
            "name": "Car",
            "occluded": true,
            "bbox": [ 686.97 , 595.25 , 785.5 , 643.5 ],
            "status": "Parked"
        },
        {
            "name": "Car",
            "occluded": true,
            "bbox": [ 690.91 , 609.68 , 752.7 , 651.4 ],
            "status": "Parked"
        },
        {
            "name": "Car",
            "occluded": true,
            "bbox": [ 613.48 , 587.38 , 727.8 , 658.0 ],
            "status": "Parked"
        },
        {
            "name": "Car",
            "occluded": true,
            "bbox": [ 612.17 , 608.37 , 689.7 , 663.2 ],
            "status": "Parked"
        },
        {
            "name": "Car",
            "occluded": true,
            "bbox": [ 234.24 , 550.63 , 603.1 , 703.9 ],
            "status": "Parked"
        },
        {
            "name": "Car",
            "occluded": true,
            "bbox": [ 20.34 , 550.63 , 502.1 , 755.1 ],
            "status": "Parked"
        },
        {
            "name": "Car",
            "occluded": false,
            "bbox": [ 0.0 , 538.82 , 279.0 , 853.5 ],
            "status": "Parked"
        },
        {
            "name": "Parking Block",
            "occluded": false,
            "bbox": [ 1732.61 , 744.3 , 1800.2 , 777.5 ]
        }
    ],
    "segmentation": [
        {
            "name": "Parking Space",
            "size": "Normal",
            "pattern": "Perpendicular",
            "polygon": [
                [ 1430.0 , 820.6 ],
                [ 1797.3 , 822.0 ],
                [ 1798.0 , 783.9 ],
                [ 1321.1 , 775.4 ]
            ]
        },
        {
            "name": "Parking Space",
            "size": "Normal",
            "pattern": "Perpendicular",
            "polygon": [
                [ 1451.56 , 825.67 ],
                [ 1652.8 , 907.31 ],
                [ 1796.5 , 906.0 ],
                [ 1795.83 , 829.47 ]
            ]
        },
        {
            "name": "Driveable Space",
            "polygon": [
                [ 1718.55 , 955.33 ],
                [ 1093.52 , 690.65 ],
                [ 1129.6 , 687.24 ],
                [ 1129.21 , 668.87 ],
                [ 1018.1 , 669.3 ],
                [ 941.69 , 631.86 ],
                [ 812.03 , 630.81 ],
                [ 2.62 , 900.87 ],
                [ 0.79 , 992.87 ],
                [ 400.9 , 961.9 ],
                [ 756.26 , 954.55 ],
                [ 1312.14 , 960.06 ],
                [ 1819.9 , 996.5 ]
            ]
        },
        {
            "name": "Parking Space",
            "size": "Normal",
            "pattern": "Perpendicular",
            "polygon": [
                [ 190.19 , 803.0 ],
                [ 250.84 , 803.52 ],
                [ 361.58 , 767.66 ],
                [ 258.75 , 765.02 ],
                [ 250.84 , 765.55 ],
                [ 242.93 , 767.66 ],
                [ 235.01 , 770.3 ],
                [ 227.1 , 773.46 ],
                [ 219.72 , 777.15 ],
                [ 212.87 , 782.96 ],
                [ 206.01 , 787.7 ],
                [ 199.15 , 791.92 ],
                [ 193.35 , 797.72 ]
            ]
        },
        {
            "name": "Parking Space",
            "size": "Normal",
            "pattern": "Perpendicular",
            "polygon": [
                [ 1311.45 , 769.03 ],
                [ 1797.3 , 779.6 ],
                [ 1698.7 , 752.6 ],
                [ 1244.36 , 746.25 ]
            ]
        }
    ],
    "bbox3d": []
}