{
    "image": "Camera/ 00000060 .jpg",
    "point_cloud": "LiDAR/ 00000060 .pcd",
    "meta": {
        "time": "Night",
        "environment": "Indoor",
        "weather": "None",
        "place": "Large",
        "city": "Gwangju",
        "terrain": "Urban",
        "road_type": "ge 4m",
        "road_material": "Paved"
    },
    "calib": {
        "intrinsic": [
            [ 1397.991371 , 0.0 , 960.0 ],
            [ 0.0 , 1397.991371 , 540.0 ],
            [ 0.0 , 0.0 , 1.0 ]
        ],
        "rotation": [ -0.96517669 , -1.502906215 , 2.560259924 ],
        "translation": [ 0.13620099 , 1.34389899 , 1.35197656 ]
    },
    "bbox2d": [
        {
            "name": "Car",
            "occluded": true,
            "bbox": [ 1335.46 , 584.35 , 1748.48 , 777.6 ],
            "status": "Parked"
        },
        {
            "name": "Car",
            "occluded": true,
            "bbox": [ 51.0 , 518.54 , 461.1 , 748.4 ],
            "status": "Parked"
        },
        {
            "name": "Car",
            "occluded": true,
            "bbox": [ 421.12 , 577.27 , 636.41 , 694.2 ],
            "status": "Parked"
        },
        {
            "name": "Car",
            "occluded": true,
            "bbox": [ 236.44 , 554.38 , 513.8 , 702.8 ],
            "status": "Parked"
        },
        {
            "name": "Car",
            "occluded": true,
            "bbox": [ 1652.8 , 590.98 , 1920.0 , 781.16 ],
            "status": "Parked"
        }
    ],
    "segmentation": [
        {
            "name": "Driveable Space",
            "polygon": [
                [ 1.26 , 997.89 ],
                [ 416.84 , 963.79 ],
                [ 827.37 , 952.42 ],
                [ 1241.68 , 960.0 ],
                [ 1640.84 , 984.0 ],
                [ 1920.0 , 1002.11 ],
                [ 1920.0 , 805.89 ],
                [ 1453.89 , 801.47 ],
                [ 1246.48 , 727.33 ],
                [ 1178.91 , 722.91 ],
                [ 1042.74 , 648.63 ],
                [ 1014.32 , 650.78 ],
                [ 992.21 , 632.84 ],
                [ 927.92 , 633.85 ],
                [ 882.69 , 636.0 ],
                [ 847.96 , 647.62 ],
                [ 797.43 , 652.8 ],
                [ 784.8 , 650.78 ],
                [ 784.8 , 670.74 ],
                [ 634.23 , 682.36 ],
                [ 620.59 , 692.84 ],
                [ 621.6 , 706.48 ],
                [ 451.07 , 722.27 ],
                [ 457.39 , 747.54 ],
                [ 395.37 , 762.32 ],
                [ 315.28 , 766.48 ],
                [ 0.0 , 770.01 ],
                [ 0.0 , 871.32 ]
            ]
        }
    ],
    "bbox3d": []
}